nbcpychecker/__init__.py
nbcpychecker/checker.py
nbcpychecker/cli.py
nbcpychecker/config.py
nbcpychecker/errors.py
nbcpychecker-1.0.2.dist-info/LICENSE
nbcpychecker-1.0.2.dist-info/METADATA
nbcpychecker-1.0.2.dist-info/WHEEL
nbcpychecker-1.0.2.dist-info/entry_points.txt
nbcpychecker-1.0.2.dist-info/RECORD
